asteroid_filterbanks/__init__.py
asteroid_filterbanks/analytic_free_fb.py
asteroid_filterbanks/deprecation.py
asteroid_filterbanks/enc_dec.py
asteroid_filterbanks/free_fb.py
asteroid_filterbanks/griffin_lim.py
asteroid_filterbanks/melgram_fb.py
asteroid_filterbanks/multiphase_gammatone_fb.py
asteroid_filterbanks/param_sinc_fb.py
asteroid_filterbanks/pcen.py
asteroid_filterbanks/scripting.py
asteroid_filterbanks/stft_fb.py
asteroid_filterbanks/torch_stft_fb.py
asteroid_filterbanks/transforms.py
asteroid_filterbanks-0.4.0.dist-info/LICENSE
asteroid_filterbanks-0.4.0.dist-info/METADATA
asteroid_filterbanks-0.4.0.dist-info/WHEEL
asteroid_filterbanks-0.4.0.dist-info/top_level.txt
asteroid_filterbanks-0.4.0.dist-info/RECORD
