Metadata-Version: 2.1
Name: asteroid-filterbanks
Version: 0.4.0
Summary: Asteroid's filterbanks
Home-page: https://github.com/asteroid-team/asteroid-filterbanks
Author: Manuel Pariente
Author-email: manuel.pariente@loria.fr
License: MIT
Platform: UNKNOWN
Classifier: Development Status :: 4 - Beta
Classifier: Programming Language :: Python :: 3
Classifier: Programming Language :: Python :: 3.6
Classifier: Programming Language :: Python :: 3.7
Classifier: Programming Language :: Python :: 3.8
Classifier: License :: OSI Approved :: MIT License
Classifier: Operating System :: OS Independent
Requires-Python: >=3.6
Provides-Extra: all
